[
    {
        "end": 7869,
        "start": 7840,
        "text": "between 01:01:20 and 01:02:55",
        "type": "DURATION",
        "value": {
            "begin": "2018-06-01T01:01:20.000",
            "end": "2018-06-01T01:02:55.000"
        }
    },
    {
        "end": 10910,
        "start": 10899,
        "text": "T01:02:49.8",
        "timex-value": "T01:02:49.008",
        "type": "DURATION",
        "value": {
            "begin": "2021-12-15T01:02:49.007",
            "end": "2021-12-15T01:02:49.009"
        }
    },
    {
        "end": 12534,
        "start": 12523,
        "text": "T01:02:50.7",
        "timex-value": "T01:02:50.007",
        "type": "DURATION",
        "value": {
            "begin": "2021-12-15T01:02:50.006",
            "end": "2021-12-15T01:02:50.008"
        }
    },
    {
        "end": 14120,
        "start": 14115,
        "text": "01:01",
        "timex-value": "T01:01",
        "type": "DURATION",
        "value": {
            "begin": "2018-06-01T01:01:00.000",
            "end": "2018-06-01T01:01:59.000"
        }
    },
    {
        "end": 14126,
        "start": 14121,
        "text": "01:02",
        "timex-value": "T01:02",
        "type": "DURATION",
        "value": {
            "begin": "2018-06-01T01:02:00.000",
            "end": "2018-06-01T01:02:59.000"
        }
    },
    {
        "end": 14132,
        "start": 14127,
        "text": "01:03",
        "timex-value": "T01:03",
        "type": "DURATION",
        "value": {
            "begin": "2018-06-01T01:03:00.000",
            "end": "2018-06-01T01:03:59.000"
        }
    },
    {
        "end": 14138,
        "start": 14133,
        "text": "01:04",
        "timex-value": "T01:04",
        "type": "DURATION",
        "value": {
            "begin": "2018-06-01T01:04:00.000",
            "end": "2018-06-01T01:04:59.000"
        }
    },
    {
        "end": 14193,
        "start": 14180,
        "text": "T01:02:45.543",
        "timex-value": "T01:02:45.543",
        "type": "DURATION",
        "value": {
            "begin": "2018-06-01T01:02:45.542",
            "end": "2018-06-01T01:02:45.544"
        }
    },
    {
        "end": 14685,
        "start": 14672,
        "text": "T01:00:36.317",
        "timex-value": "T01:00:36.317",
        "type": "DURATION",
        "value": {
            "begin": "2018-06-01T01:00:36.316",
            "end": "2018-06-01T01:00:36.318"
        }
    },
    {
        "end": 14703,
        "start": 14690,
        "text": "T01:02:14.343",
        "timex-value": "T01:02:14.343",
        "type": "DURATION",
        "value": {
            "begin": "2018-06-01T01:02:14.342",
            "end": "2018-06-01T01:02:14.344"
        }
    },
    {
        "end": 14725,
        "start": 14712,
        "text": "T01:02:45.543",
        "timex-value": "T01:02:45.543",
        "type": "DURATION",
        "value": {
            "begin": "2018-06-01T01:02:45.542",
            "end": "2018-06-01T01:02:45.544"
        }
    },
    {
        "end": 15703,
        "start": 15678,
        "text": "from 01:02:32 to 01:02:46",
        "type": "DURATION",
        "value": {
            "begin": "2021-12-15T01:02:32.000",
            "end": "2021-12-15T01:02:46.000"
        }
    },
    {
        "end": 16652,
        "start": 16644,
        "text": "01:01:10",
        "timex-value": "T01:01:10",
        "type": "DURATION",
        "value": {
            "begin": "2021-12-15T01:01:10.495",
            "end": "2021-12-15T01:01:10.505"
        }
    },
    {
        "end": 16671,
        "start": 16663,
        "text": "01:02:20",
        "timex-value": "T01:02:20",
        "type": "DURATION",
        "value": {
            "begin": "2021-12-15T01:02:20.495",
            "end": "2021-12-15T01:02:20.505"
        }
    },
    {
        "end": 17095,
        "start": 17066,
        "text": "between 01:01:10 and 01:02:20",
        "type": "DURATION",
        "value": {
            "begin": "2021-12-15T01:01:10.000",
            "end": "2021-12-15T01:02:20.000"
        }
    },
    {
        "end": 20947,
        "start": 20939,
        "text": "01:02:54",
        "timex-value": "T01:02:54",
        "type": "DURATION",
        "value": {
            "begin": "2018-06-01T01:02:54.495",
            "end": "2018-06-01T01:02:54.505"
        }
    },
    {
        "end": 20956,
        "start": 20948,
        "text": "01:02:48",
        "timex-value": "T01:02:48",
        "type": "DURATION",
        "value": {
            "begin": "2018-06-01T01:02:48.495",
            "end": "2018-06-01T01:02:48.505"
        }
    },
    {
        "end": 20965,
        "start": 20957,
        "text": "01:02:50",
        "timex-value": "T01:02:50",
        "type": "DURATION",
        "value": {
            "begin": "2018-06-01T01:02:50.495",
            "end": "2018-06-01T01:02:50.505"
        }
    },
    {
        "end": 20974,
        "start": 20966,
        "text": "01:02:52",
        "timex-value": "T01:02:52",
        "type": "DURATION",
        "value": {
            "begin": "2018-06-01T01:02:52.495",
            "end": "2018-06-01T01:02:52.505"
        }
    },
    {
        "end": 22154,
        "start": 22141,
        "text": "T01:02:38.043",
        "timex-value": "T01:02:38.043",
        "type": "DURATION",
        "value": {
            "begin": "2018-06-01T01:02:38.042",
            "end": "2018-06-01T01:02:38.044"
        }
    },
    {
        "end": 22190,
        "start": 22177,
        "text": "10:00 - 10:00",
        "type": "DURATION",
        "value": {
            "begin": "2018-06-01T10:00:00.000",
            "end": "2018-06-01T10:00:00.000"
        }
    },
    {
        "end": 22239,
        "start": 22226,
        "text": "T01:02:50.793",
        "timex-value": "T01:02:50.793",
        "type": "DURATION",
        "value": {
            "begin": "2018-06-01T01:02:50.792",
            "end": "2018-06-01T01:02:50.794"
        }
    },
    {
        "end": 22273,
        "start": 22260,
        "text": "10:00 - 10:00",
        "type": "DURATION",
        "value": {
            "begin": "2018-06-01T10:00:00.000",
            "end": "2018-06-01T10:00:00.000"
        }
    },
    {
        "end": 22289,
        "start": 22276,
        "text": "10:00 - 10:00",
        "type": "DURATION",
        "value": {
            "begin": "2018-06-01T10:00:00.000",
            "end": "2018-06-01T10:00:00.000"
        }
    },
    {
        "end": 22400,
        "start": 22389,
        "text": "T01:02:49.5",
        "timex-value": "T01:02:49.005",
        "type": "DURATION",
        "value": {
            "begin": "2018-06-01T01:02:49.004",
            "end": "2018-06-01T01:02:49.006"
        }
    },
    {
        "end": 24773,
        "start": 24764,
        "text": "02:49",
        "timex-value": "T02:49",
        "type": "DURATION",
        "value": {
            "begin": "2018-06-01T02:49:00.000",
            "end": "2018-06-01T02:49:59.000"
        }
    },
    {
        "end": 24784,
        "start": 24777,
        "text": "02:50",
        "timex-value": "T02:50",
        "type": "DURATION",
        "value": {
            "begin": "2018-06-01T02:50:00.000",
            "end": "2018-06-01T02:50:59.000"
        }
    },
    {
        "end": 24827,
        "start": 24803,
        "text": "2018-06-01/T01:02:49.833",
        "timex-value": "2018-06-01T01:02:49.833",
        "type": "DURATION",
        "value": {
            "begin": "2018-06-01T01:02:49.832",
            "end": "2018-06-01T01:02:49.834"
        }
    },
    {
        "end": 24869,
        "start": 24860,
        "text": "02:51",
        "timex-value": "T02:51",
        "type": "DURATION",
        "value": {
            "begin": "2018-06-01T02:51:00.000",
            "end": "2018-06-01T02:51:59.000"
        }
    },
    {
        "end": 24928,
        "start": 24904,
        "text": "2018-06-01/T01:02:50.883",
        "timex-value": "2018-06-01T01:02:50.883",
        "type": "DURATION",
        "value": {
            "begin": "2018-06-01T01:02:50.882",
            "end": "2018-06-01T01:02:50.884"
        }
    },
    {
        "end": 25395,
        "start": 25382,
        "text": "T01:02:49.833",
        "timex-value": "T01:02:49.833",
        "type": "DURATION",
        "value": {
            "begin": "2018-06-01T01:02:49.832",
            "end": "2018-06-01T01:02:49.834"
        }
    },
    {
        "end": 25413,
        "start": 25400,
        "text": "T01:02:50.883",
        "timex-value": "T01:02:50.883",
        "type": "DURATION",
        "value": {
            "begin": "2018-06-01T01:02:50.882",
            "end": "2018-06-01T01:02:50.884"
        }
    },
    {
        "end": 25430,
        "start": 25422,
        "text": "01:02:54",
        "timex-value": "T01:02:54",
        "type": "DURATION",
        "value": {
            "begin": "2018-06-01T01:02:54.495",
            "end": "2018-06-01T01:02:54.505"
        }
    },
    {
        "end": 25552,
        "start": 25534,
        "text": "02:51.0 2018-06-01",
        "timex-value": "2018-06-01T02:51",
        "type": "DURATION",
        "value": {
            "begin": "2018-06-01T02:51:00.000",
            "end": "2018-06-01T02:51:59.000"
        }
    },
    {
        "end": 25582,
        "start": 25558,
        "text": "2018-06-01/T01:02:51.747",
        "timex-value": "2018-06-01T01:02:51.747",
        "type": "DURATION",
        "value": {
            "begin": "2018-06-01T01:02:51.746",
            "end": "2018-06-01T01:02:51.748"
        }
    },
    {
        "end": 27177,
        "start": 27164,
        "text": "00:42 - 00:58",
        "type": "DURATION",
        "value": {
            "begin": "2021-12-15T00:42:00.000",
            "end": "2021-12-15T00:58:00.000"
        }
    },
    {
        "end": 27641,
        "start": 27636,
        "text": "00:42",
        "timex-value": "T00:42",
        "type": "DURATION",
        "value": {
            "begin": "2018-06-01T00:42:00.000",
            "end": "2018-06-01T00:42:59.000"
        }
    },
    {
        "end": 27647,
        "start": 27642,
        "text": "00:45",
        "timex-value": "T00:45",
        "type": "DURATION",
        "value": {
            "begin": "2018-06-01T00:45:00.000",
            "end": "2018-06-01T00:45:59.000"
        }
    },
    {
        "end": 27653,
        "start": 27648,
        "text": "00:48",
        "timex-value": "T00:48",
        "type": "DURATION",
        "value": {
            "begin": "2018-06-01T00:48:00.000",
            "end": "2018-06-01T00:48:59.000"
        }
    },
    {
        "end": 27659,
        "start": 27654,
        "text": "00:51",
        "timex-value": "T00:51",
        "type": "DURATION",
        "value": {
            "begin": "2018-06-01T00:51:00.000",
            "end": "2018-06-01T00:51:59.000"
        }
    },
    {
        "end": 27665,
        "start": 27660,
        "text": "00:54",
        "timex-value": "T00:54",
        "type": "DURATION",
        "value": {
            "begin": "2018-06-01T00:54:00.000",
            "end": "2018-06-01T00:54:59.000"
        }
    },
    {
        "end": 27671,
        "start": 27666,
        "text": "00:57",
        "timex-value": "T00:57",
        "type": "DURATION",
        "value": {
            "begin": "2018-06-01T00:57:00.000",
            "end": "2018-06-01T00:57:59.000"
        }
    },
    {
        "end": 27680,
        "start": 27672,
        "text": "00:58:01",
        "timex-value": "T00:58:01",
        "type": "DURATION",
        "value": {
            "begin": "2018-06-01T00:58:01.495",
            "end": "2018-06-01T00:58:01.505"
        }
    },
    {
        "end": 27730,
        "start": 27725,
        "text": "16:32",
        "timex-value": "T16:32",
        "type": "DURATION",
        "value": {
            "begin": "2018-06-01T16:32:00.000",
            "end": "2018-06-01T16:32:59.000"
        }
    },
    {
        "end": 27736,
        "start": 27731,
        "text": "15:24",
        "timex-value": "T15:24",
        "type": "DURATION",
        "value": {
            "begin": "2018-06-01T15:24:00.000",
            "end": "2018-06-01T15:24:59.000"
        }
    },
    {
        "end": 27747,
        "start": 27742,
        "text": "10:13",
        "timex-value": "T10:13",
        "type": "DURATION",
        "value": {
            "begin": "2018-06-01T10:13:00.000",
            "end": "2018-06-01T10:13:59.000"
        }
    },
    {
        "end": 27752,
        "start": 27748,
        "text": "8:37",
        "timex-value": "T08:37",
        "type": "DURATION",
        "value": {
            "begin": "2018-06-01T08:37:00.000",
            "end": "2018-06-01T08:37:59.000"
        }
    },
    {
        "end": 27757,
        "start": 27753,
        "text": "7:48",
        "timex-value": "T07:48",
        "type": "DURATION",
        "value": {
            "begin": "2018-06-01T07:48:00.000",
            "end": "2018-06-01T07:48:59.000"
        }
    },
    {
        "end": 27762,
        "start": 27758,
        "text": "7:37",
        "timex-value": "T07:37",
        "type": "DURATION",
        "value": {
            "begin": "2018-06-01T07:37:00.000",
            "end": "2018-06-01T07:37:59.000"
        }
    }
]